ikun/__init__.py
ikun-1.0.dist-info/METADATA
ikun-1.0.dist-info/WHEEL
ikun-1.0.dist-info/top_level.txt
ikun-1.0.dist-info/RECORD
