Metadata-Version: 2.1
Name: ikun
Version: 1.0
Summary: 这是第一个对外发布的模块，测试哦
Author: joker
Author-email: lsc_1219@163.com
